cbseg
