Metadata-Version: 2.1
Name: cbseg
Version: 1.0.0
Summary: Python package for Circular Binary Segmentation
Home-page: https://github.com/kylessmtih/cbseg
Author: Kyle S. Smith
Author-email: kyle.smith@stjude.org
License: GPL2
Keywords: cython circular binaray segmentation c
Platform: Linux
Classifier: Development Status :: 4 - Beta
Classifier: Environment :: Console
Classifier: Intended Audience :: Developers
Classifier: Intended Audience :: Science/Research
Classifier: Operating System :: POSIX :: Linux
Classifier: Programming Language :: Cython
Classifier: Programming Language :: Python
Classifier: Programming Language :: Python :: 3
Classifier: Programming Language :: Python :: 3.4
Classifier: Topic :: Scientific/Engineering
Classifier: Topic :: Scientific/Engineering :: Mathematics
Classifier: Topic :: Software Development :: Libraries
Classifier: Topic :: Software Development :: Libraries :: Python Modules
Provides: cbseg
